{
  "timestamp": "2025-05-17T21:29:29.419123+00:00",
  "shark_trades": [
    {
      "symbol": "AAPL",
      "average_price": 172.33,
      "total_volume": 191852,
      "average_volume": 95926,
      "last_seen": "2025-05-17T21:29:29.419056+00:00",
      "confidence": "Medium"
    },
    {
      "symbol": "AAPL",
      "average_price": 349.66,
      "total_volume": 250707,
      "average_volume": 125353,
      "last_seen": "2025-05-17T21:29:29.419068+00:00",
      "confidence": "High"
    },
    {
      "symbol": "NVDA",
      "average_price": 397.17,
      "total_volume": 445439,
      "average_volume": 222719,
      "last_seen": "2025-05-17T21:29:29.419076+00:00",
      "confidence": "High"
    },
    {
      "symbol": "TSLA",
      "average_price": 133.37,
      "total_volume": 245020,
      "average_volume": 122510,
      "last_seen": "2025-05-17T21:29:29.419082+00:00",
      "confidence": "High"
    },
    {
      "symbol": "TSLA",
      "average_price": 499.51,
      "total_volume": 445103,
      "average_volume": 222551,
      "last_seen": "2025-05-17T21:29:29.419086+00:00",
      "confidence": "Medium"
    },
    {
      "symbol": "TSLA",
      "average_price": 498.14,
      "total_volume": 303088,
      "average_volume": 151544,
      "last_seen": "2025-05-17T21:29:29.419090+00:00",
      "confidence": "Medium"
    },
    {
      "symbol": "AMD",
      "average_price": 401.64,
      "total_volume": 484710,
      "average_volume": 242355,
      "last_seen": "2025-05-17T21:29:29.419096+00:00",
      "confidence": "High"
    },
    {
      "symbol": "META",
      "average_price": 419.35,
      "total_volume": 346762,
      "average_volume": 173381,
      "last_seen": "2025-05-17T21:29:29.419103+00:00",
      "confidence": "Medium"
    },
    {
      "symbol": "MSFT",
      "average_price": 301.07,
      "total_volume": 170699,
      "average_volume": 85349,
      "last_seen": "2025-05-17T21:29:29.419108+00:00",
      "confidence": "Medium"
    },
    {
      "symbol": "AMZN",
      "average_price": 245.14,
      "total_volume": 283814,
      "average_volume": 141907,
      "last_seen": "2025-05-17T21:29:29.419113+00:00",
      "confidence": "Low"
    },
    {
      "symbol": "GOOG",
      "average_price": 446.12,
      "total_volume": 284611,
      "average_volume": 142305,
      "last_seen": "2025-05-17T21:29:29.419117+00:00",
      "confidence": "Medium"
    },
    {
      "symbol": "GOOG",
      "average_price": 113.98,
      "total_volume": 190366,
      "average_volume": 95183,
      "last_seen": "2025-05-17T21:29:29.419121+00:00",
      "confidence": "Medium"
    }
  ]
}