{
  "timestamp": "2025-05-19T22:40:18.697569+00:00",
  "shark_trades": [
    {
      "symbol": "AAPL",
      "average_price": 187.58,
      "total_volume": 184261,
      "average_volume": 92130,
      "last_seen": "2025-05-19T22:40:18.697477+00:00",
      "confidence": "Medium"
    },
    {
      "symbol": "AAPL",
      "average_price": 253.27,
      "total_volume": 246947,
      "average_volume": 123473,
      "last_seen": "2025-05-19T22:40:18.697490+00:00",
      "confidence": "High"
    },
    {
      "symbol": "AAPL",
      "average_price": 292.92,
      "total_volume": 218931,
      "average_volume": 109465,
      "last_seen": "2025-05-19T22:40:18.697496+00:00",
      "confidence": "Medium"
    },
    {
      "symbol": "NVDA",
      "average_price": 210.9,
      "total_volume": 108251,
      "average_volume": 54125,
      "last_seen": "2025-05-19T22:40:18.697502+00:00",
      "confidence": "High"
    },
    {
      "symbol": "NVDA",
      "average_price": 204.35,
      "total_volume": 304801,
      "average_volume": 152400,
      "last_seen": "2025-05-19T22:40:18.697506+00:00",
      "confidence": "High"
    },
    {
      "symbol": "NVDA",
      "average_price": 174.5,
      "total_volume": 461535,
      "average_volume": 230767,
      "last_seen": "2025-05-19T22:40:18.697510+00:00",
      "confidence": "High"
    },
    {
      "symbol": "TSLA",
      "average_price": 462.27,
      "total_volume": 138012,
      "average_volume": 69006,
      "last_seen": "2025-05-19T22:40:18.697516+00:00",
      "confidence": "High"
    },
    {
      "symbol": "TSLA",
      "average_price": 495.03,
      "total_volume": 461432,
      "average_volume": 230716,
      "last_seen": "2025-05-19T22:40:18.697521+00:00",
      "confidence": "Medium"
    },
    {
      "symbol": "TSLA",
      "average_price": 487.42,
      "total_volume": 81884,
      "average_volume": 40942,
      "last_seen": "2025-05-19T22:40:18.697525+00:00",
      "confidence": "High"
    },
    {
      "symbol": "AMD",
      "average_price": 145.4,
      "total_volume": 385936,
      "average_volume": 192968,
      "last_seen": "2025-05-19T22:40:18.697530+00:00",
      "confidence": "Low"
    },
    {
      "symbol": "AMD",
      "average_price": 282.06,
      "total_volume": 71430,
      "average_volume": 35715,
      "last_seen": "2025-05-19T22:40:18.697534+00:00",
      "confidence": "Low"
    },
    {
      "symbol": "META",
      "average_price": 442.67,
      "total_volume": 496564,
      "average_volume": 248282,
      "last_seen": "2025-05-19T22:40:18.697539+00:00",
      "confidence": "Low"
    },
    {
      "symbol": "META",
      "average_price": 119.5,
      "total_volume": 238830,
      "average_volume": 119415,
      "last_seen": "2025-05-19T22:40:18.697543+00:00",
      "confidence": "High"
    },
    {
      "symbol": "MSFT",
      "average_price": 173.57,
      "total_volume": 220195,
      "average_volume": 110097,
      "last_seen": "2025-05-19T22:40:18.697547+00:00",
      "confidence": "High"
    },
    {
      "symbol": "MSFT",
      "average_price": 322.69,
      "total_volume": 208905,
      "average_volume": 104452,
      "last_seen": "2025-05-19T22:40:18.697551+00:00",
      "confidence": "Medium"
    },
    {
      "symbol": "AMZN",
      "average_price": 358.41,
      "total_volume": 460582,
      "average_volume": 230291,
      "last_seen": "2025-05-19T22:40:18.697555+00:00",
      "confidence": "Medium"
    },
    {
      "symbol": "AMZN",
      "average_price": 219.69,
      "total_volume": 110071,
      "average_volume": 55035,
      "last_seen": "2025-05-19T22:40:18.697559+00:00",
      "confidence": "Medium"
    },
    {
      "symbol": "AMZN",
      "average_price": 379.48,
      "total_volume": 134758,
      "average_volume": 67379,
      "last_seen": "2025-05-19T22:40:18.697563+00:00",
      "confidence": "High"
    },
    {
      "symbol": "GOOG",
      "average_price": 214.94,
      "total_volume": 275545,
      "average_volume": 137772,
      "last_seen": "2025-05-19T22:40:18.697567+00:00",
      "confidence": "High"
    }
  ]
}