{
  "timestamp": "2025-05-15T13:38:00.678831",
  "timestamp": "2025-05-15T13:47:25.069389",
  "whale_trades": [
    {
      "symbol": "NVDA",
      "type": "CALL",
      "strike": 95.0,
      "expiration": "2025-05-16",
      "premium": 1713364.2000000002,
      "open_interest": 42621,
      "last_price": 40.2
    },
    {
      "symbol": "NVDA",
      "type": "CALL",
      "strike": 110.0,
      "expiration": "2025-05-16",
      "premium": 1698199.76,
      "open_interest": 67096,
      "last_price": 25.31
    },
    {
      "symbol": "NVDA",
      "type": "CALL",
      "strike": 100.0,
      "expiration": "2025-05-16",
      "premium": 1568574.0,
      "open_interest": 44310,
      "last_price": 35.4
    },
    {
      "symbol": "NVDA",
      "type": "CALL",
      "strike": 5.0,
      "expiration": "2025-05-16",
      "premium": 1263830.05,
      "open_interest": 9733,
      "last_price": 129.85
    },
    {
      "symbol": "NVDA",
      "type": "CALL",
      "strike": 115.0,
      "expiration": "2025-05-16",
      "premium": 1073325.5999999999,
      "open_interest": 52614,
      "last_price": 20.4
    }
  ]
}
